odoo/addons/sale_stock_product_pack/README.rst
odoo/addons/sale_stock_product_pack/__init__.py
odoo/addons/sale_stock_product_pack/__manifest__.py
odoo/addons/sale_stock_product_pack/i18n/sale_stock_product_pack.pot
odoo/addons/sale_stock_product_pack/models/__init__.py
odoo/addons/sale_stock_product_pack/models/sale_order.py
odoo/addons/sale_stock_product_pack/readme/CONTRIBUTORS.rst
odoo/addons/sale_stock_product_pack/readme/DESCRIPTION.rst
odoo/addons/sale_stock_product_pack/readme/ROADMAP.rst
odoo/addons/sale_stock_product_pack/static/description/icon.png
odoo/addons/sale_stock_product_pack/static/description/index.html
odoo/addons/sale_stock_product_pack/tests/__init__.py
odoo/addons/sale_stock_product_pack/tests/test_sale_stock_product_pack.py
odoo13_addon_sale_stock_product_pack-13.0.1.0.2.dist-info/METADATA
odoo13_addon_sale_stock_product_pack-13.0.1.0.2.dist-info/WHEEL
odoo13_addon_sale_stock_product_pack-13.0.1.0.2.dist-info/top_level.txt
odoo13_addon_sale_stock_product_pack-13.0.1.0.2.dist-info/RECORD
